kotti_restful_api
