Metadata-Version: 1.1
Name: kotti-restful-api
Version: 0.1.1
Summary: Restful API for Kotti
Home-page: https://github.com/b4oshany/kotti_restful_api
Author: Oshane Bailey
Author-email: b4.oshany@gmail.com
License: BSD-derived (http://www.repoze.org/LICENSE.txt)
Keywords: kotti restful api json cross domain web cms wcms pylons pyramid sqlalchemy bootstrap
Platform: UNKNOWN
Classifier: Programming Language :: Python
Classifier: Programming Language :: Python :: 2.7
Classifier: Framework :: Pylons
Classifier: Topic :: Internet :: WWW/HTTP
Classifier: Topic :: Internet :: WWW/HTTP :: Dynamic Content
Classifier: Topic :: Internet :: WWW/HTTP :: WSGI :: Application
Classifier: License :: Repoze Public License
